jsonschema_pyref/__init__.py
jsonschema_pyref/examples/__init__.py
jsonschema_pyref/examples/schema1.json
jsonschema_pyref/examples/schema2.yml
jsonschema_pyref/examples/schema3.json
jsonschema_pyref/examples/schema4.yml
jsonschema_pyref-0.1.0.dist-info/LICENSE
jsonschema_pyref-0.1.0.dist-info/METADATA
jsonschema_pyref-0.1.0.dist-info/WHEEL
jsonschema_pyref-0.1.0.dist-info/top_level.txt
jsonschema_pyref-0.1.0.dist-info/RECORD
