Metadata-Version: 2.1
Name: jsonschema-pyref
Version: 0.1.0
Summary: Supports referencing schemas from Python packages
Home-page: https://gitlab.com/mlgenetics/jsonschema-pyref
Author: E. Madison Bray
Maintainer-email: embray@lri.fr
License: UNKNOWN
Platform: UNKNOWN
Classifier: Development Status :: 4 - Beta
Classifier: Intended Audience :: Developers
Classifier: License :: OSI Approved :: BSD License
Classifier: Operating System :: OS Independent
Classifier: Programming Language :: Python :: 3.7
Classifier: Programming Language :: Python :: 3.8
Classifier: Programming Language :: Python :: 3.9
Classifier: Programming Language :: Python :: 3.10
Classifier: Typing :: Typed
Requires-Python: >=3.7
Requires-Dist: jsonschema
Provides-Extra: docs
Requires-Dist: m2r2 ; extra == 'docs'
Requires-Dist: sphinx ; extra == 'docs'
Requires-Dist: sphinx-rtd-theme ; extra == 'docs'
Requires-Dist: sphinxcontrib-napoleon ; extra == 'docs'
Requires-Dist: sphinxcontrib-spelling ; extra == 'docs'
Provides-Extra: tests
Requires-Dist: flake8 (<4) ; extra == 'tests'
Requires-Dist: pytest ; extra == 'tests'
Requires-Dist: pytest-flake8 ; extra == 'tests'
Requires-Dist: pytest-mypy ; extra == 'tests'
Requires-Dist: pyyaml ; extra == 'tests'
Provides-Extra: yaml
Requires-Dist: pyyaml ; extra == 'yaml'
